zillionare/__init__.py
zillionare/zillionare.py
zillionare-0.1.0.dist-info/AUTHORS.rst
zillionare-0.1.0.dist-info/LICENSE
zillionare-0.1.0.dist-info/METADATA
zillionare-0.1.0.dist-info/WHEEL
zillionare-0.1.0.dist-info/top_level.txt
zillionare-0.1.0.dist-info/RECORD
