Metadata-Version: 2.1
Name: zillionare
Version: 0.1.0
Summary: AI量化交易
Home-page: https://github.com/zillionare/zillionare
Author: Aaron Yang
Author-email: code@jieyu.ai
License: MIT license
Keywords: zillionare
Platform: UNKNOWN
Classifier: Development Status :: 2 - Pre-Alpha
Classifier: Intended Audience :: Developers
Classifier: License :: OSI Approved :: MIT License
Classifier: Natural Language :: English
Classifier: Programming Language :: Python :: 3
Classifier: Programming Language :: Python :: 3.5
Classifier: Programming Language :: Python :: 3.6
Classifier: Programming Language :: Python :: 3.7
Classifier: Programming Language :: Python :: 3.8
Requires-Python: >=3.5
